setup.py
jenkinsconnector/__init__.py
jenkinsconnector.egg-info/PKG-INFO
jenkinsconnector.egg-info/SOURCES.txt
jenkinsconnector.egg-info/dependency_links.txt
jenkinsconnector.egg-info/not-zip-safe
jenkinsconnector.egg-info/requires.txt
jenkinsconnector.egg-info/top_level.txt