Metadata-Version: 1.0
Name: jenkinsconnector
Version: 0.1.1
Summary: A library to communicate with jenkins
Home-page: https://github.com/AxiaCore/jenkins-connector
Author: AxiaCore
Author-email: info@axiacore.com
License: MIT
Platform: UNKNOWN
